resnets/__init__.py
resnets/jax/__init__.py
resnets/pytorch/__init__.py
resnets/tensorflow/__init__.py
resnets-0.0.1.dist-info/METADATA
resnets-0.0.1.dist-info/WHEEL
resnets-0.0.1.dist-info/licenses/LICENSE
resnets-0.0.1.dist-info/RECORD
