Metadata-Version: 2.3
Name: resnets
Version: 0.0.1
Project-URL: Repository, https://github.com/sjmikler/resnets
Project-URL: Issues, https://github.com/sjmikler/resnets/issues
Author-email: Szymon Mikler <sjmikler@gmail.com>
Maintainer-email: Szymon Mikler <sjmikler@gmail.com>
License: MIT License
License-File: LICENSE
Classifier: Development Status :: 4 - Beta
Classifier: Intended Audience :: Developers
Classifier: License :: OSI Approved :: MIT License
Classifier: Operating System :: OS Independent
Classifier: Programming Language :: Python :: 3
Classifier: Programming Language :: Python :: 3.7
Classifier: Programming Language :: Python :: 3.8
Classifier: Programming Language :: Python :: 3.9
Classifier: Programming Language :: Python :: 3.10
Classifier: Programming Language :: Python :: 3.11
Classifier: Programming Language :: Python :: 3.12
Requires-Python: >=3.7
Requires-Dist: progress-table
